random_bode_generator/__init__.py
random_bode_generator-1.1.9.dist-info/METADATA
random_bode_generator-1.1.9.dist-info/WHEEL
random_bode_generator-1.1.9.dist-info/top_level.txt
random_bode_generator-1.1.9.dist-info/RECORD
