Metadata-Version: 2.1
Name: random-bode-generator
Version: 1.1.9
Summary: package for generating random Bode plots intelligently
Home-page: https://github.com/ryanGT/random_bode_generator
Author: Ryan Krauss
Author-email: ryanwkrauss@gmail.com
License: UNKNOWN
Platform: UNKNOWN
Classifier: Programming Language :: Python :: 3
Classifier: License :: OSI Approved :: MIT License
Classifier: Operating System :: OS Independent
